fooddetect/__init__.py
fooddetect/fooddetect.py
fooddetection-0.0.3.dist-info/METADATA
fooddetection-0.0.3.dist-info/WHEEL
fooddetection-0.0.3.dist-info/top_level.txt
fooddetection-0.0.3.dist-info/RECORD
