Metadata-Version: 2.1
Name: fooddetection
Version: 0.0.3
Summary: This library makes it possible to detect food in an image and make the non-food parts transparent.
Home-page: https://github.com/Yuki-max/FoodDetection.py
Author: Yuki-max
Author-email: yuki65763933@gmail.com
License: UNKNOWN
Platform: UNKNOWN
Classifier: Programming Language :: Python :: 3.7
Classifier: Programming Language :: Python :: 3.8
Classifier: Programming Language :: Python :: 3.9
Classifier: License :: OSI Approved :: MIT License
Classifier: Operating System :: OS Independent
